<?xml version="1.0" encoding="utf-8" ?>
<odoo>

    <record id="spp_service_point_device_view_search" model="ir.ui.view">
        <field name="name">spp.service.point.device.view.search</field>
        <field name="model">spp.service.point.device</field>
        <field name="arch" type="xml">
            <search string="Terminal Device">
                <field name="name" filter_domain="[('name', 'ilike', self)]" />
                <field name="service_point_terminal_device_id" />
                <filter name="fltr_active" string="Active" domain="[('is_active', '=', True)]" />
                <separator />
                <filter name="fltr_not_active" string="Disabled" domain="[('is_active', '=', False)]" />
                <group expand="1" string="Group By">
                    <filter
                        name="grp_android_version"
                        string="Android Ver."
                        context="{'group_by': 'android_version'}"
                    />
                    <filter name="grp_device_model" string="Model" context="{'group_by': 'device_model'}" />
                </group>
            </search>
        </field>
    </record>

    <record id="spp_service_point_device_view_tree" model="ir.ui.view">
        <field name="name">spp.service.point.device.view.tree</field>
        <field name="model">spp.service.point.device</field>
        <field name="arch" type="xml">
            <tree>
                <field name="name" />
                <field name="service_point_terminal_device_id" />
                <field name="is_active" />
            </tree>
        </field>
    </record>

    <record id="spp_service_point_device_view_form" model="ir.ui.view">
        <field name="name">spp.service.point.device.view.form</field>
        <field name="model">spp.service.point.device</field>
        <field name="arch" type="xml">
            <form string="Terminal Device">
                <header>
                    <button
                        string="Inactive"
                        name="action_change_is_active"
                        type="object"
                        invisible="not is_active"
                    />
                    <button
                        string="Active"
                        name="action_change_is_active"
                        type="object"
                        class="oe_highlight"
                        invisible="is_active"
                    />
                </header>
                <sheet>
                    <h1>
                        <field name="name" />
                    </h1>
                    <notebook>
                        <page name="info" string="Info.">
                            <group>
                                <group>
                                    <field name="device_model" />
                                    <field name="android_version" />
                                    <field name="service_point_terminal_device_id" />
                                </group>
                                <group>
                                    <field name="service_point_id" />
                                    <field name="is_active" />
                                </group>
                            </group>
                        </page>
                    </notebook>
                </sheet>
            </form>
        </field>
    </record>

</odoo>
